setup.py
dwight_chroot/__init__.py
dwight_chroot/__version__.py
dwight_chroot/cache.py
dwight_chroot/config.py
dwight_chroot/environment.py
dwight_chroot/exceptions.py
dwight_chroot/include.py
dwight_chroot/platform_utils.py
dwight_chroot/python_compat.py
dwight_chroot/resources.py
dwight_chroot.egg-info/PKG-INFO
dwight_chroot.egg-info/SOURCES.txt
dwight_chroot.egg-info/dependency_links.txt
dwight_chroot.egg-info/entry_points.txt
dwight_chroot.egg-info/namespace_packages.txt
dwight_chroot.egg-info/top_level.txt
dwight_chroot/scripts/__init__.py
dwight_chroot/scripts/dwight.py