Metadata-Version: 1.1
Name: dwight-chroot
Version: 0.0.2
Summary: Utility for creating and managing Linux based isolated development environments, using chroot
Home-page: UNKNOWN
Author: Rotem Yaari
Author-email: vmalloc@gmail.com
License: BSD
Platform: UNKNOWN
Classifier: Programming Language :: Python :: 2.7
